bcrypt/__init__.py
bcrypt/__init__.pyi
bcrypt/_bcrypt.pypy39-pp73-aarch64-linux-gnu.so
bcrypt/py.typed
bcrypt-4.1.1.dist-info/LICENSE
bcrypt-4.1.1.dist-info/METADATA
bcrypt-4.1.1.dist-info/WHEEL
bcrypt-4.1.1.dist-info/top_level.txt
bcrypt-4.1.1.dist-info/RECORD
