Metadata-Version: 2.1
Name: bcrypt
Version: 4.1.1
Summary: Modern password hashing for your software and your servers
Author-email: The Python Cryptographic Authority developers <cryptography-dev@python.org>
License: Apache-2.0
Project-URL: homepage, https://github.com/pyca/bcrypt/
Classifier: Development Status :: 5 - Production/Stable
Classifier: License :: OSI Approved :: Apache Software License
Classifier: Programming Language :: Python :: Implementation :: CPython
Classifier: Programming Language :: Python :: Implementation :: PyPy
Classifier: Programming Language :: Python :: 3
Classifier: Programming Language :: Python :: 3 :: Only
Classifier: Programming Language :: Python :: 3.7
Classifier: Programming Language :: Python :: 3.8
Classifier: Programming Language :: Python :: 3.9
Classifier: Programming Language :: Python :: 3.10
Classifier: Programming Language :: Python :: 3.11
Classifier: Programming Language :: Python :: 3.12
Requires-Python: >=3.7
License-File: LICENSE
Provides-Extra: tests
Requires-Dist: pytest!=3.3.0,>=3.2.1; extra == "tests"
Provides-Extra: typecheck
Requires-Dist: mypy; extra == "typecheck"
